{
  "metadata": {
    "id": "010",
    "title": {
      "en": "How koreans say \"Let's eat soon\" — Is it a real invitation?",
      "ko": "조만간 밥 한번 먹자! (한국식 인사치레와 다음 기약하기)"
    },
    "description": {
      "en": "Don't get fooled! Learn the secret behind the famous Korean farewell \"Let's grab a meal sometime\" and how to respond naturally.",
      "ko": "\"언제 밥 한번 먹자\" 라는 말, 진짜 약속일까요? 한국인들의 정겨운 인사치레에 당황하지 않고 센스 있게 대답하는 리액션을 배워봅니다."
    },
    "duration": {
      "en": "",
      "ko": ""
    },
    "level": "Beginner-Intermediate",
    "tags": [
      "Situation. Social. Greeting. Culture. Farewell. Relationship. Season 2"
    ],
    "course": "real-reaction-2",
    "youtube": "",
    "full_audio": ""
  },
  "content": [
    {
      "type": "Intro",
      "speaker": "John",
      "emotion": "살짝 헷갈린다는 목소리로 바로 시작",
      "text": "Mina. I’ve been waiting for a phone call for a week! A Korean friend told me. \"밥 한번 먹자\" which means \"Let's have a meal.\"",
      "translation": "",
      "lang": "EN",
      "audio": "RR_010_s001.mp3",
      "playable": false,
      "seq": 1,
      "insight": null
    },
    {
      "type": "Intro",
      "speaker": "John",
      "emotion": "",
      "text": "But I haven't heard anything from him. Is he ghosting me, or did I miss something?",
      "translation": "",
      "lang": "EN",
      "audio": "RR_010_s002.mp3",
      "playable": false,
      "seq": 2,
      "insight": null
    },
    {
      "type": "Intro",
      "speaker": "Mina",
      "emotion": "미소 지으며",
      "text": "그건 한국 사람들의 아주 전형적인 '인사치레' 예요.",
      "translation": "That is a very typical '인사치레' of Korean people.",
      "lang": "KO",
      "audio": "RR_010_s003.mp3",
      "playable": true,
      "seq": 3,
      "insight": null
    },
    {
      "type": "Intro",
      "speaker": "Mina",
      "emotion": "",
      "text": "헤어질 때 아쉬움을 담아서..., \"다음에 꼭 다시 보자\" 라는 뜻으로 하는 말이죠.",
      "translation": "It's something people say when parting to mean \"Let's definitely see each other again.\"",
      "lang": "KO",
      "audio": "RR_010_s004.mp3",
      "playable": true,
      "seq": 4,
      "insight": null
    },
    {
      "type": "Intro",
      "speaker": "John",
      "emotion": "깨달으며",
      "text": "Ah, so it's more like a warm \"See you later\" than a concrete plan?",
      "translation": "",
      "lang": "EN",
      "audio": "RR_010_s005.mp3",
      "playable": false,
      "seq": 5,
      "insight": null
    },
    {
      "type": "Intro",
      "speaker": "Mina",
      "emotion": "",
      "text": "정확해요! 구체적인 날짜를 잡지 않는다면 그냥 기분 좋은 인사로 받아들이면 돼요.",
      "translation": "Exactly! If they don't set a specific date, you can just take it as a pleasant greeting.",
      "lang": "KO",
      "audio": "RR_010_s006.mp3",
      "playable": true,
      "seq": 6,
      "insight": null
    },
    {
      "type": "Intro",
      "speaker": "Mina",
      "emotion": "",
      "text": "오늘은 이런 인사치레에 센스 있게 화답하는 법을 배워볼게요!",
      "translation": "Today, we'll learn how to respond to these greetings with style!",
      "lang": "KO",
      "audio": "RR_010_s007.mp3",
      "playable": true,
      "seq": 7,
      "insight": null
    },
    {
      "type": "Vocab",
      "speaker": "John",
      "emotion": "흥미로워하며",
      "text": "조만간 밥 한번 먹어요. So I can say this too when I want to be friendly?",
      "translation": "",
      "lang": "EN",
      "audio": "RR_010_s008.mp3",
      "playable": false,
      "seq": 8,
      "insight": null
    },
    {
      "type": "Vocab",
      "speaker": "Mina",
      "emotion": "",
      "text": "네! \"당신과 계속 친하게 지내고 싶다\" 라는 뜻을 전달하는 아주 좋은 리액션이에요.",
      "translation": "Yes! It's a very good reaction to convey the meaning \"I want to continue to be close to you.\"",
      "lang": "KO",
      "audio": "RR_010_s009.mp3",
      "playable": true,
      "seq": 9,
      "insight": {
        "title": "조만간 밥 한번 먹어요",
        "description": "'Let's grab a meal sometime'",
        "usage_tip": "'조만간(Sometime soon)' + '밥(Meal)' + '한번(Once)' + '먹어요(Eat)'. This is the most common Korean farewell phrase that shows friendliness."
      }
    },
    {
      "type": "Vocab",
      "speaker": "John",
      "emotion": "따라하며",
      "text": "네. 좋아요! 조만간 밥 한번 먹어요.",
      "translation": "Yes, great! Let's have a meal sometime soon.",
      "lang": "KO",
      "audio": "RR_010_s010.mp3",
      "playable": true,
      "seq": 10,
      "insight": null
    },
    {
      "type": "Vocab",
      "speaker": "John",
      "emotion": "궁금해하며",
      "text": "What if I want to make sure it's a real plan?",
      "translation": "",
      "lang": "EN",
      "audio": "RR_010_s011.mp3",
      "playable": false,
      "seq": 11,
      "insight": null
    },
    {
      "type": "Vocab",
      "speaker": "Mina",
      "emotion": "",
      "text": "그럴 땐 \"언제가 좋으세요?\" 라고 구체적으로 물어보세요.",
      "translation": "In that case, ask specifically, \"언제가 좋으세요?\".",
      "lang": "KO",
      "audio": "RR_010_s012.mp3",
      "playable": true,
      "seq": 12,
      "insight": null
    },
    {
      "type": "Vocab",
      "speaker": "Mina",
      "emotion": "",
      "text": "날짜를 정하기 시작하면 그때부터는 진짜 약속이 되는 거예요!",
      "translation": "Once you start picking a date, it becomes a real appointment from then on!",
      "lang": "KO",
      "audio": "RR_010_s013.mp3",
      "playable": true,
      "seq": 13,
      "insight": {
        "title": "언제가 좋으세요?",
        "description": "'When would be good for you?'",
        "usage_tip": "'언제(When)' + '가(Subject marker)' + '좋으세요(Is good/Polite)'. Use this to turn a vague greeting into a real plan."
      }
    },
    {
      "type": "Dial",
      "speaker": "John",
      "emotion": "상황극 시작",
      "text": "Okay, let's jump in. I just ran into an old colleague on the street.",
      "translation": "",
      "lang": "EN",
      "audio": "RR_010_s014.mp3",
      "playable": false,
      "seq": 14,
      "insight": null
    },
    {
      "type": "Dial",
      "speaker": "Mina",
      "emotion": "반갑게",
      "text": "어? 존! 여기서 다 만나네요. 잘 지냈어요?",
      "translation": "Oh, Mr. John! What a surprise to see you here. Have you been well?",
      "lang": "KO",
      "audio": "RR_010_s015.mp3",
      "playable": true,
      "seq": 15,
      "insight": null
    },
    {
      "type": "Dial",
      "speaker": "John",
      "emotion": "미소 지으며",
      "text": "미나! 정말 반가워요. 연락하려고 했는데 제가 좀 바빴네요.",
      "translation": "Yes, Mina! It's so good to see you. I was going to call you, but I've been a bit busy.",
      "lang": "KO",
      "audio": "RR_010_s016.mp3",
      "playable": true,
      "seq": 16,
      "insight": null
    },
    {
      "type": "Dial",
      "speaker": "Mina",
      "emotion": "가야 할 듯 시계를 보며",
      "text": "저도요! 우리 오늘 아쉽지만 이만 가봐야겠네요. 조만간 밥 한번 먹어요!",
      "translation": "Me too! It's a shame, but I guess we have to go now. Let's have a meal sometime soon!",
      "lang": "KO",
      "audio": "RR_010_s017.mp3",
      "playable": true,
      "seq": 17,
      "insight": {
        "title": "조만간 밥 한번 먹어요",
        "description": "Social Courtesy",
        "usage_tip": "Mina is using this to end the conversation warmly since she's in a hurry."
      }
    },
    {
      "type": "Dial",
      "speaker": "John",
      "emotion": "활기차게 맞장구치며",
      "text": "네. 좋아요! 제가 조만간 연락드릴게요.",
      "translation": "Yes, great! I'll contact you sometime soon.",
      "lang": "KO",
      "audio": "RR_010_s018.mp3",
      "playable": true,
      "seq": 18,
      "insight": {
        "title": "제가 조만간 연락드릴게요",
        "description": "Friendly Response",
        "usage_tip": "Even if you don't call right away, this is a perfect way to match the other person's friendly vibe."
      }
    },
    {
      "type": "Dial",
      "speaker": "Mina",
      "emotion": "",
      "text": "그래요. 꼭 연락해요! 안녕!",
      "translation": "Okay, make sure to call! Bye!",
      "lang": "KO",
      "audio": "RR_010_s019.mp3",
      "playable": true,
      "seq": 19,
      "insight": null
    },
    {
      "type": "Outro",
      "speaker": "John",
      "emotion": "유쾌하게",
      "text": "I see. It’s not a lie; it’s just a way of showing affection and keeping the door open!",
      "translation": "",
      "lang": "EN",
      "audio": "RR_010_s020.mp3",
      "playable": false,
      "seq": 20,
      "insight": null
    },
    {
      "type": "Outro",
      "speaker": "Mina",
      "emotion": "",
      "text": "맞아요. 한국어 리액션의 핵심은 단어의 뜻보다 그 속에 담긴 '따뜻한 마음' 을 읽는 거예요.",
      "translation": "Right. The core of Korean reactions is reading the 'warm heart' inside rather than just the meaning of the words.",
      "lang": "KO",
      "audio": "RR_010_s021.mp3",
      "playable": true,
      "seq": 21,
      "insight": null
    },
    {
      "type": "Outro",
      "speaker": "John",
      "emotion": "정리하며",
      "text": "Let's review our \"future promise\" reactions one last time.",
      "translation": "",
      "lang": "EN",
      "audio": "RR_010_s022.mp3",
      "playable": false,
      "seq": 22,
      "insight": null
    },
    {
      "type": "Outro",
      "speaker": "John",
      "emotion": "",
      "text": "조만간 밥 한번 먹어요!",
      "translation": "Let's have a meal sometime!",
      "lang": "KO",
      "audio": "RR_010_s023.mp3",
      "playable": true,
      "seq": 23,
      "insight": null
    },
    {
      "type": "Outro",
      "speaker": "John",
      "emotion": "",
      "text": "제가 연락드릴게요!",
      "translation": "I'll contact you!",
      "lang": "KO",
      "audio": "RR_010_s024.mp3",
      "playable": true,
      "seq": 24,
      "insight": null
    },
    {
      "type": "Outro",
      "speaker": "John",
      "emotion": "",
      "text": "언제가 좋으세요?",
      "translation": "When would be good for you?",
      "lang": "KO",
      "audio": "RR_010_s025.mp3",
      "playable": true,
      "seq": 25,
      "insight": null
    },
    {
      "type": "Outro",
      "speaker": "John",
      "emotion": "",
      "text": "조만간 꼭 봐요!",
      "translation": "Let's see each other soon for sure!",
      "lang": "KO",
      "audio": "RR_010_s026.mp3",
      "playable": true,
      "seq": 26,
      "insight": null
    },
    {
      "type": "Outro",
      "speaker": "John",
      "emotion": "",
      "text": "조심히 가세요!",
      "translation": "Go safely! / Get home safely!",
      "lang": "KO",
      "audio": "RR_010_s027.mp3",
      "playable": true,
      "seq": 27,
      "insight": null
    },
    {
      "type": "Outro",
      "speaker": "Mina",
      "emotion": "",
      "text": "여러분도 오늘 헤어지는 친구에게 따뜻하게 말해 보세요. \"조만간 밥 한번 먹자!\"",
      "translation": "Everyone, try saying it warmly to a friend you're parting with today. \"Let's grab a meal sometime!\"",
      "lang": "KO",
      "audio": "RR_010_s028.mp3",
      "playable": true,
      "seq": 28,
      "insight": null
    },
    {
      "type": "Outro",
      "speaker": "John",
      "emotion": "",
      "text": "That's all for today. We've finished Part 1 of Season 2!",
      "translation": "",
      "lang": "EN",
      "audio": "RR_010_s029.mp3",
      "playable": false,
      "seq": 29,
      "insight": null
    },
    {
      "type": "Outro",
      "speaker": "Mina",
      "emotion": "손을 흔들며",
      "text": "우리 다음 파트에서 더 재미있는 상황으로 만나요. 안녕~!",
      "translation": "Let's meet with more fun situations in the next part. Bye~!",
      "lang": "KO",
      "audio": "RR_010_s030.mp3",
      "playable": true,
      "seq": 30,
      "insight": null
    }
  ],
  "vocabulary": [
    {
      "word": "인사치레",
      "meaning": "Social courtesy / Formal greeting",
      "example": "\"밥 한번 먹자\"는 말은 한국인들의 대표적인 인사치레예요. (\"Let's eat sometime\" is a representative social courtesy of Koreans.)",
      "audio": "RR_010_v001.mp3",
      "seq": 1
    },
    {
      "word": "조만간",
      "meaning": "Sometime soon / Before long",
      "example": "조만간 좋은 소식을 들려드릴 수 있을 것 같아요. (I think I'll be able to tell you some good news sometime soon.)",
      "audio": "RR_010_v002.mp3",
      "seq": 2
    },
    {
      "word": "전형적",
      "meaning": "Typical / Classic",
      "example": "그의 대답은 전형적인 한국식 거절 표현이었어요. (His answer was a typical Korean expression of refusal.)",
      "audio": "RR_010_v003.mp3",
      "seq": 3
    },
    {
      "word": "구체적",
      "meaning": "Specific / Concrete",
      "example": "좀 더 구체적인 계획을 세우는 게 좋겠어요. (It would be better to make a more specific plan.)",
      "audio": "RR_010_v004.mp3",
      "seq": 4
    },
    {
      "word": "화답하다",
      "meaning": "To respond / To reciprocate",
      "example": "그녀의 친절에 밝은 미소로 화답했어요. (I responded to her kindness with a bright smile.)",
      "audio": "RR_010_v005.mp3",
      "seq": 5
    },
    {
      "word": "정겹다",
      "meaning": "To be warm / Heart-warming",
      "example": "친구들과 정겹게 인사를 나누며 헤어졌어요. (I parted with my friends while exchanging warm greetings.)",
      "audio": "RR_010_v006.mp3",
      "seq": 6
    }
  ]
}